Workbook

Sheet Simulador
A1: APP Invest
A4: Simulador de investimento mensal
A6: PREMISSAS DA SIMULAÇÃO | F6: RESULTADOS ESTIMADOS
A7: Quanto investir por mês? | B7: =B42 -> 500 | C7: 200 | D7: Calculado pela soma dos aportes em FIIs abaixo | F7: Valor total investido | G7: {=INDEX(Projeção!D4:D484,B9*12+1)} -> 35000
A8: Valor inicial | B8: 5000 | C8: 200 | D8: Patrimônio já disponível no início | F8: Patrimônio acumulado | G8: {=INDEX(Projeção!E4:E484,B9*12+1)} -> 46333.165
A9: Por quanto tempo? | B9: 5 | C9: anos | D9: Prazo máximo sugerido: 40 anos | F9: Rendimento acumulado | G9: =G8-G7 -> 11333.165
A10: Taxa de rendimento | B10: 0.1 | C10: ao ano | D10: Convertida automaticamente para taxa mensal equivalente | F10: Dividendos mensais | G10: =G8*B11/12 -> 397.693
A11: Dividend yield | B11: =C42 -> 0.103 | C11: ao ano | D11: Média ponderada pelos aportes em cada tipo de FII | F11: Rentabilidade total | G11: =IFERROR(G9/G7,0) -> 0.32380472
A12: Reajuste anual do aporte | B12: 0 | C12: ao ano | D12: Aumenta o aporte a cada 12 meses | F12: Taxa mensal equivalente | G12: =(1+B10)^(1/12)-1 -> 0.0079741404
F14: Cenário ilustrativo; impostos, inflação e taxas não estão descontados.
A36: CARTEIRA DE FUNDOS IMOBILIÁRIOS (FIIs) | F36: COMPOSIÇÃO DO RETORNO
A37: Tipo de fundo | B37: Aporte mensal | C37: Dividend yield a.a. | D37: Dividendos mensais estimados | F37: Componente | G37: Valor
A38: FIIs de Papel | B38: 200 | C38: 0.12 | D38: =IFERROR($G$8*(B38/$B$42)*C38/12,0) -> 185.33266 | F38: Valor investido | G38: =G7 -> 35000
A39: FIIs de Tijolo | B39: 150 | C39: 0.09 | D39: =IFERROR($G$8*(B39/$B$42)*C39/12,0) -> 104.24962 | F39: Rendimentos | G39: =G9 -> 11333.165
A40: FIIs Híbridos | B40: 100 | C40: 0.1 | D40: =IFERROR($G$8*(B40/$B$42)*C40/12,0) -> 77.221942
A41: Fundos de Fundos (FOFs) | B41: 50 | C41: 0.08 | D41: =IFERROR($G$8*(B41/$B$42)*C41/12,0) -> 30.888777
A42: Total / média ponderada | B42: =SUM(B38:B41) -> 500 | C42: =IFERROR(SUMPRODUCT(B38:B41,C38:C41)/B42,0) -> 0.103 | D42: =SUM(D38:D41) -> 397.693
A44: Edite os aportes e as taxas nas células amarelas; todos os totais, projeções, dividendos e gráficos serão recalculados automaticamente.

Sheet Projeção
A1: PROJEÇÃO MENSAL — APP Invest
A3: Mês | B3: Data | C3: Aporte mensal | D3: Total investido | E3: Patrimônio acumulado | F3: Dividendos/mês
A4: 0 | B4: =TODAY() -> 46292 | C4: 0 | D4: =Simulador!B8 -> 5000 | E4: =Simulador!B8 -> 5000 | F4: =E4*Simulador!B11/12 -> 42.916667
A5: =IF(ROW()-4<=Simulador!$B$9*12,ROW()-4,NA()) -> 1 | B5: =IFERROR(EDATE($B$4,A5),NA()) -> 46322 | C5: =IFERROR(Simulador!$B$7*(1+Simulador!$B$12)^INT((A5-1)/12),NA()) -> 500 | D5: =IFERROR(D4+C5,NA()) -> 5500 | E5: =IFERROR(E4*(1+Simulador!$G$12)+C5,NA()) -> 5539.8707 | F5: =IFERROR(E5*Simulador!$B$11/12,NA()) -> 47.550557
A6: =IF(ROW()-4<=Simulador!$B$9*12,ROW()-4,NA()) -> 2 | B6: =IFERROR(EDATE($B$4,A6),NA()) -> 46353 | C6: =IFERROR(Simulador!$B$7*(1+Simulador!$B$12)^INT((A6-1)/12),NA()) -> 500 | D6: =IFERROR(D5+C6,NA()) -> 6000 | E6: =IFERROR(E5*(1+Simulador!$G$12)+C6,NA()) -> 6084.0464 | F6: =IFERROR(E6*Simulador!$B$11/12,NA()) -> 52.221398
A7: =IF(ROW()-4<=Simulador!$B$9*12,ROW()-4,NA()) -> 3 | B7: =IFERROR(EDATE($B$4,A7),NA()) -> 46383 | C7: =IFERROR(Simulador!$B$7*(1+Simulador!$B$12)^INT((A7-1)/12),NA()) -> 500 | D7: =IFERROR(D6+C7,NA()) -> 6500 | E7: =IFERROR(E6*(1+Simulador!$G$12)+C7,NA()) -> 6632.5614 | F7: =IFERROR(E7*Simulador!$B$11/12,NA()) -> 56.929486
A8: =IF(ROW()-4<=Simulador!$B$9*12,ROW()-4,NA()) -> 4 | B8: =IFERROR(EDATE($B$4,A8),NA()) -> 46414 | C8: =IFERROR(Simulador!$B$7*(1+Simulador!$B$12)^INT((A8-1)/12),NA()) -> 500 | D8: =IFERROR(D7+C8,NA()) -> 7000 | E8: =IFERROR(E7*(1+Simulador!$G$12)+C8,NA()) -> 7185.4504 | F8: =IFERROR(E8*Simulador!$B$11/12,NA()) -> 61.675116
A9: =IF(ROW()-4<=Simulador!$B$9*12,ROW()-4,NA()) -> 5 | B9: =IFERROR(EDATE($B$4,A9),NA()) -> 46445 | C9: =IFERROR(Simulador!$B$7*(1+Simulador!$B$12)^INT((A9-1)/12),NA()) -> 500 | D9: =IFERROR(D8+C9,NA()) -> 7500 | E9: =IFERROR(E8*(1+Simulador!$G$12)+C9,NA()) -> 7742.7482 | F9: =IFERROR(E9*Simulador!$B$11/12,NA()) -> 66.458589
A10: =IF(ROW()-4<=Simulador!$B$9*12,ROW()-4,NA()) -> 6 | B10: =IFERROR(EDATE($B$4,A10),NA()) -> 46473 | C10: =IFERROR(Simulador!$B$7*(1+Simulador!$B$12)^INT((A10-1)/12),NA()) -> 500 | D10: =IFERROR(D9+C10,NA()) -> 8000 | E10: =IFERROR(E9*(1+Simulador!$G$12)+C10,NA()) -> 8304.49 | F10: =IFERROR(E10*Simulador!$B$11/12,NA()) -> 71.280206
A11: =IF(ROW()-4<=Simulador!$B$9*12,ROW()-4,NA()) -> 7 | B11: =IFERROR(EDATE($B$4,A11),NA()) -> 46504 | C11: =IFERROR(Simulador!$B$7*(1+Simulador!$B$12)^INT((A11-1)/12),NA()) -> 500 | D11: =IFERROR(D10+C11,NA()) -> 8500 | E11: =IFERROR(E10*(1+Simulador!$G$12)+C11,NA()) -> 8870.7111 | F11: =IFERROR(E11*Simulador!$B$11/12,NA()) -> 76.140271
A12: =IF(ROW()-4<=Simulador!$B$9*12,ROW()-4,NA()) -> 8 | B12: =IFERROR(EDATE($B$4,A12),NA()) -> 46534 | C12: =IFERROR(Simulador!$B$7*(1+Simulador!$B$12)^INT((A12-1)/12),NA()) -> 500 | D12: =IFERROR(D11+C12,NA()) -> 9000 | E12: =IFERROR(E11*(1+Simulador!$G$12)+C12,NA()) -> 9441.4474 | F12: =IFERROR(E12*Simulador!$B$11/12,NA()) -> 81.039091
A13: =IF(ROW()-4<=Simulador!$B$9*12,ROW()-4,NA()) -> 9 | B13: =IFERROR(EDATE($B$4,A13),NA()) -> 46565 | C13: =IFERROR(Simulador!$B$7*(1+Simulador!$B$12)^INT((A13-1)/12),NA()) -> 500 | D13: =IFERROR(D12+C13,NA()) -> 9500 | E13: =IFERROR(E12*(1+Simulador!$G$12)+C13,NA()) -> 10016.735 | F13: =IFERROR(E13*Simulador!$B$11/12,NA()) -> 85.976974
A14: =IF(ROW()-4<=Simulador!$B$9*12,ROW()-4,NA()) -> 10 | B14: =IFERROR(EDATE($B$4,A14),NA()) -> 46595 | C14: =IFERROR(Simulador!$B$7*(1+Simulador!$B$12)^INT((A14-1)/12),NA()) -> 500 | D14: =IFERROR(D13+C14,NA()) -> 10000 | E14: =IFERROR(E13*(1+Simulador!$G$12)+C14,NA()) -> 10596.61 | F14: =IFERROR(E14*Simulador!$B$11/12,NA()) -> 90.954233
A15: =IF(ROW()-4<=Simulador!$B$9*12,ROW()-4,NA()) -> 11 | B15: =IFERROR(EDATE($B$4,A15),NA()) -> 46626 | C15: =IFERROR(Simulador!$B$7*(1+Simulador!$B$12)^INT((A15-1)/12),NA()) -> 500 | D15: =IFERROR(D14+C15,NA()) -> 10500 | E15: =IFERROR(E14*(1+Simulador!$G$12)+C15,NA()) -> 11181.109 | F15: =IFERROR(E15*Simulador!$B$11/12,NA()) -> 95.971182
A16: =IF(ROW()-4<=Simulador!$B$9*12,ROW()-4,NA()) -> 12 | B16: =IFERROR(EDATE($B$4,A16),NA()) -> 46657 | C16: =IFERROR(Simulador!$B$7*(1+Simulador!$B$12)^INT((A16-1)/12),NA()) -> 500 | D16: =IFERROR(D15+C16,NA()) -> 11000 | E16: =IFERROR(E15*(1+Simulador!$G$12)+C16,NA()) -> 11770.268 | F16: =IFERROR(E16*Simulador!$B$11/12,NA()) -> 101.02814
... A484: =IF(ROW()-4<=Simulador!$B$9*12,ROW()-4,NA()) -> #N/A | B484: =IFERROR(EDATE($B$4,A484),NA()) -> #N/A | C484: =IFERROR(Simulador!$B$7*(1+Simulador!$B$12)^INT((A484-1)/12),NA()) -> #N/A | D484: =IFERROR(D483+C484,NA()) -> #N/A | E484: =IFERROR(E483*(1+Simulador!$G$12)+C484,NA()) -> #N/A | F484: =IFERROR(E484*Simulador!$B$11/12,NA()) -> #N/A
